rivven/_rivven.cpython-312-darwin.so
rivven-0.0.4.dist-info/METADATA
rivven-0.0.4.dist-info/WHEEL
rivven-0.0.4.dist-info/RECORD
