Metadata-Version: 2.4
Name: rivven
Version: 0.0.4
Classifier: Development Status :: 4 - Beta
Classifier: Intended Audience :: Developers
Classifier: License :: OSI Approved :: Apache Software License
Classifier: Programming Language :: Python :: 3
Classifier: Programming Language :: Python :: 3.8
Classifier: Programming Language :: Python :: 3.9
Classifier: Programming Language :: Python :: 3.10
Classifier: Programming Language :: Python :: 3.11
Classifier: Programming Language :: Python :: 3.12
Classifier: Programming Language :: Python :: Implementation :: CPython
Classifier: Programming Language :: Rust
Classifier: Topic :: Software Development :: Libraries :: Python Modules
Classifier: Topic :: System :: Distributed Computing
Classifier: Framework :: AsyncIO
Classifier: Typing :: Typed
Requires-Dist: pytest>=7.0 ; extra == 'dev'
Requires-Dist: pytest-asyncio>=0.21 ; extra == 'dev'
Requires-Dist: mypy>=1.0 ; extra == 'dev'
Requires-Dist: ruff>=0.1 ; extra == 'dev'
Provides-Extra: dev
Summary: High-performance Python client for Rivven distributed streaming platform
Keywords: streaming,kafka,messaging,distributed,async
License: Apache-2.0
Requires-Python: >=3.8
Project-URL: Documentation, https://github.com/hupe1980/rivven/tree/main/crates/rivven-python
Project-URL: Homepage, https://github.com/hupe1980/rivven
Project-URL: Repository, https://github.com/hupe1980/rivven
